odoo8_addon_l10n_fr_intrastat_product-8.0.2.0.0.99.dev32-py3.8-nspkg.pth
odoo_addons/l10n_fr_intrastat_product/README.rst
odoo_addons/l10n_fr_intrastat_product/__init__.py
odoo_addons/l10n_fr_intrastat_product/__openerp__.py
odoo_addons/l10n_fr_intrastat_product/company.py
odoo_addons/l10n_fr_intrastat_product/company_view.xml
odoo_addons/l10n_fr_intrastat_product/intrastat_demo.xml
odoo_addons/l10n_fr_intrastat_product/intrastat_product.py
odoo_addons/l10n_fr_intrastat_product/intrastat_product_reminder.xml
odoo_addons/l10n_fr_intrastat_product/intrastat_product_view.xml
odoo_addons/l10n_fr_intrastat_product/intrastat_transaction.py
odoo_addons/l10n_fr_intrastat_product/intrastat_transaction_data.xml
odoo_addons/l10n_fr_intrastat_product/intrastat_transaction_view.xml
odoo_addons/l10n_fr_intrastat_product/partner.py
odoo_addons/l10n_fr_intrastat_product/partner_view.xml
odoo_addons/l10n_fr_intrastat_product/product.py
odoo_addons/l10n_fr_intrastat_product/product_view.xml
odoo_addons/l10n_fr_intrastat_product/purchase.py
odoo_addons/l10n_fr_intrastat_product/stock.py
odoo_addons/l10n_fr_intrastat_product/data/deb.xsd
odoo_addons/l10n_fr_intrastat_product/i18n/am.po
odoo_addons/l10n_fr_intrastat_product/i18n/ar.po
odoo_addons/l10n_fr_intrastat_product/i18n/bg.po
odoo_addons/l10n_fr_intrastat_product/i18n/bs.po
odoo_addons/l10n_fr_intrastat_product/i18n/ca.po
odoo_addons/l10n_fr_intrastat_product/i18n/ca_ES.po
odoo_addons/l10n_fr_intrastat_product/i18n/cs.po
odoo_addons/l10n_fr_intrastat_product/i18n/da.po
odoo_addons/l10n_fr_intrastat_product/i18n/da_DK.po
odoo_addons/l10n_fr_intrastat_product/i18n/de.po
odoo_addons/l10n_fr_intrastat_product/i18n/el_GR.po
odoo_addons/l10n_fr_intrastat_product/i18n/en_GB.po
odoo_addons/l10n_fr_intrastat_product/i18n/es.po
odoo_addons/l10n_fr_intrastat_product/i18n/es_AR.po
odoo_addons/l10n_fr_intrastat_product/i18n/es_CL.po
odoo_addons/l10n_fr_intrastat_product/i18n/es_CO.po
odoo_addons/l10n_fr_intrastat_product/i18n/es_CR.po
odoo8_addon_l10n_fr_intrastat_product-8.0.2.0.0.99.dev32.dist-info/METADATA
odoo8_addon_l10n_fr_intrastat_product-8.0.2.0.0.99.dev32.dist-info/WHEEL
odoo8_addon_l10n_fr_intrastat_product-8.0.2.0.0.99.dev32.dist-info/namespace_packages.txt
odoo8_addon_l10n_fr_intrastat_product-8.0.2.0.0.99.dev32.dist-info/top_level.txt
odoo8_addon_l10n_fr_intrastat_product-8.0.2.0.0.99.dev32.dist-info/RECORD
