Metadata-Version: 2.1
Name: odoo8-addon-l10n-fr-intrastat-product
Version: 8.0.2.0.0.99.dev32
Summary: Module for Intrastat product reporting (DEB) for France
Home-page: http://www.akretion.com
Author: Akretion
License: AGPL-3
Platform: UNKNOWN
Classifier: Programming Language :: Python
Classifier: Framework :: Odoo
Classifier: Framework :: Odoo :: 8.0
Classifier: License :: OSI Approved :: GNU Affero General Public License v3
Requires-Python: ~=2.7
Requires-Dist: odoo8-addon-intrastat-product
Requires-Dist: odoo8-addon-l10n-fr-department
Requires-Dist: odoo8-addon-l10n-fr-siret
Requires-Dist: odoo (<9.0a,>=8.0a)
